MANIFEST.in
setup.py
hoarder/__init__.py
hoarder/backends.py
hoarder/ga.py
hoarder/middleware.py
hoarder/models.py
hoarder/mongo.py
hoarder/tasks.py
hoarder/tests.py
hoarder/views.py
hoarder.egg-info/PKG-INFO
hoarder.egg-info/SOURCES.txt
hoarder.egg-info/dependency_links.txt
hoarder.egg-info/requires.txt
hoarder.egg-info/top_level.txt
hoarder/templates/hoarder/ga.html
hoarder/templates/hoarder/km.html
hoarder/templatetags/__init__.py
hoarder/templatetags/hoarder_tags.py