Metadata-Version: 1.0
Name: hoarder
Version: 0.0.6
Summary: Django analytics kit for the data-obsessed.
Home-page: https://github.com/InviteBox/hoarder
Author: Alexander Tereshkin
Author-email: atereshkin@invitebox.com
License: BSD
Keywords: django analytics
Platform: UNKNOWN
Classifier: Development Status :: 3 - Alpha
Classifier: Topic :: Software Development
Classifier: Framework :: Django
Classifier: Intended Audience :: Developers
Classifier: License :: OSI Approved :: BSD License
